htmltomd/__init__.py
htmltomd-0.2.0.dist-info/METADATA
htmltomd-0.2.0.dist-info/WHEEL
htmltomd-0.2.0.dist-info/licenses/LICENSE
htmltomd-0.2.0.dist-info/RECORD
