Metadata-Version: 2.1
Name: htmltomd
Version: 0.2.0
Summary: HTML to Markdown
Project-URL: Homepage, https://github.com/taptorestart/htmltomd
Project-URL: Bug Tracker, https://github.com/taptorestart/htmltomd/issues
Author-email: Tap to restart <taptorestart@example.com>
License-File: LICENSE
Keywords: html,markdown,md
Classifier: License :: OSI Approved :: MIT License
Classifier: Operating System :: OS Independent
Classifier: Programming Language :: Python :: 3
Requires-Python: >=3.6
